[{"gametype_short":"ctf","map_name":"courtyard","rating":25.600000381469727,"games":128,"win_pct":58,"percentile":61},{"gametype_short":"ctf","map_name":"japanesecastles","rating":23.75,"games":565,"win_pct":57,"percentile":60},{"gametype_short":"ctf","map_name":"shiningforces","rating":22.950000762939453,"games":54,"win_pct":56,"percentile":41},{"gametype_short":"ctf","map_name":"ironworks","rating":22.709999084472656,"games":430,"win_pct":51,"percentile":42},{"gametype_short":"ctf","map_name":"troubledwaters","rating":22.010000228881836,"games":215,"win_pct":47,"percentile":24},{"gametype_short":"ctf","map_name":"infinity","rating":21.450000762939453,"games":312,"win_pct":47,"percentile":25},{"gametype_short":"ctf","map_name":"q3wcp9","rating":21.31999969482422,"games":553,"win_pct":49,"percentile":35},{"gametype_short":"ctf","map_name":"pillbox","rating":20.079999923706055,"games":28,"win_pct":64,"percentile":51},{"gametype_short":"tdm","map_name":"tornado","rating":31.260000228881836,"games":13,"win_pct":54,"percentile":83},{"gametype_short":"tdm","map_name":"grimdungeons","rating":29.860000610351562,"games":12,"win_pct":67,"percentile":82},{"gametype_short":"tdm","map_name":"limbus","rating":28.110000610351562,"games":143,"win_pct":57,"percentile":75},{"gametype_short":"tdm","map_name":"ragnarok","rating":27.979999542236328,"games":106,"win_pct":58,"percentile":74},{"gametype_short":"tdm","map_name":"hiddenfortress","rating":26.549999237060547,"games":272,"win_pct":57,"percentile":68},{"gametype_short":"tdm","map_name":"dreadfulplace","rating":26.1299991607666,"games":139,"win_pct":53,"percentile":68},{"gametype_short":"tdm","map_name":"purgatory","rating":25.719999313354492,"games":235,"win_pct":56,"percentile":65},{"gametype_short":"tdm","map_name":"deepinside","rating":24.690000534057617,"games":44,"win_pct":48,"percentile":46},{"gametype_short":"tdm","map_name":"campgrounds","rating":23.350000381469727,"games":13,"win_pct":46,"percentile":41},{"gametype_short":"tdm","map_name":"intervention","rating":18.56999969482422,"games":12,"win_pct":33,"percentile":19}]