[{"timestamp":1577133934,"gametype_short":"ctf","rating":27.479999542236328,"game_num":1},{"timestamp":1577394355,"gametype_short":"ctf","rating":31.600000381469727,"game_num":2},{"timestamp":1577396033,"gametype_short":"ctf","rating":29.399999618530273,"game_num":3},{"timestamp":1577397904,"gametype_short":"ctf","rating":26.989999771118164,"game_num":4},{"timestamp":1577475248,"gametype_short":"ctf","rating":29.270000457763672,"game_num":5},{"timestamp":1577476596,"gametype_short":"ctf","rating":27.530000686645508,"game_num":6},{"timestamp":1577480155,"gametype_short":"ctf","rating":25.780000686645508,"game_num":7},{"timestamp":1577481947,"gametype_short":"ctf","rating":24.079999923706055,"game_num":8},{"timestamp":1577565166,"gametype_short":"ctf","rating":21.709999084472656,"game_num":9},{"timestamp":1577634531,"gametype_short":"ctf","rating":20.440000534057617,"game_num":10},{"timestamp":1577635908,"gametype_short":"ctf","rating":22.09000015258789,"game_num":11},{"timestamp":1577742624,"gametype_short":"ctf","rating":23.09000015258789,"game_num":12},{"timestamp":1577818140,"gametype_short":"tdm","rating":28.399999618530273,"game_num":1},{"timestamp":1577821700,"gametype_short":"tdm","rating":24.93000030517578,"game_num":2},{"timestamp":1577823866,"gametype_short":"tdm","rating":22.270000457763672,"game_num":3},{"timestamp":1578435331,"gametype_short":"ctf","rating":21.84000015258789,"game_num":13},{"timestamp":1578779899,"gametype_short":"ctf","rating":22.799999237060547,"game_num":14},{"timestamp":1579894340,"gametype_short":"ctf","rating":21.969999313354492,"game_num":15},{"timestamp":1579896235,"gametype_short":"ctf","rating":22.950000762939453,"game_num":16},{"timestamp":1579899673,"gametype_short":"ctf","rating":23.8700008392334,"game_num":17},{"timestamp":1579903579,"gametype_short":"ctf","rating":24.6200008392334,"game_num":18},{"timestamp":1579905462,"gametype_short":"ctf","rating":25.450000762939453,"game_num":19},{"timestamp":1579981440,"gametype_short":"ctf","rating":24.790000915527344,"game_num":20},{"timestamp":1579984407,"gametype_short":"ctf","rating":24.049999237060547,"game_num":21},{"timestamp":1580758359,"gametype_short":"ctf","rating":24.979999542236328,"game_num":22},{"timestamp":1580762002,"gametype_short":"ctf","rating":24.25,"game_num":23},{"timestamp":1580766234,"gametype_short":"ctf","rating":23.56999969482422,"game_num":24},{"timestamp":1580768166,"gametype_short":"ctf","rating":22.940000534057617,"game_num":25},{"timestamp":1580852434,"gametype_short":"ctf","rating":22.459999084472656,"game_num":26},{"timestamp":1580854444,"gametype_short":"ctf","rating":21.979999542236328,"game_num":27},{"timestamp":1580936661,"gametype_short":"ctf","rating":21.31999969482422,"game_num":28},{"timestamp":1580938666,"gametype_short":"ctf","rating":21.959999084472656,"game_num":29},{"timestamp":1581022054,"gametype_short":"ctf","rating":21.440000534057617,"game_num":30},{"timestamp":1581026017,"gametype_short":"ctf","rating":20.860000610351562,"game_num":31},{"timestamp":1581108557,"gametype_short":"ctf","rating":20.31999969482422,"game_num":32},{"timestamp":1581114378,"gametype_short":"ctf","rating":20.90999984741211,"game_num":33},{"timestamp":1581116283,"gametype_short":"ctf","rating":20.260000228881836,"game_num":34},{"timestamp":1581188098,"gametype_short":"ctf","rating":19.770000457763672,"game_num":35},{"timestamp":1581190848,"gametype_short":"ctf","rating":19.34000015258789,"game_num":36},{"timestamp":1581192799,"gametype_short":"ctf","rating":18.56999969482422,"game_num":37},{"timestamp":1581204596,"gametype_short":"ctf","rating":18.06999969482422,"game_num":38},{"timestamp":1581277805,"gametype_short":"ctf","rating":17.559999465942383,"game_num":39},{"timestamp":1581281090,"gametype_short":"ctf","rating":18,"game_num":40},{"timestamp":1581282995,"gametype_short":"ctf","rating":18.34000015258789,"game_num":41},{"timestamp":1581286672,"gametype_short":"ctf","rating":18.649999618530273,"game_num":42},{"timestamp":1581366245,"gametype_short":"ctf","rating":19.3700008392334,"game_num":43},{"timestamp":1581368105,"gametype_short":"ctf","rating":19.1200008392334,"game_num":44},{"timestamp":1581446066,"gametype_short":"ctf","rating":18.56999969482422,"game_num":45},{"timestamp":1581448051,"gametype_short":"ctf","rating":17.860000610351562,"game_num":46},{"timestamp":1581451473,"gametype_short":"ctf","rating":18.450000762939453,"game_num":47},{"timestamp":1581453043,"gametype_short":"ctf","rating":18.81999969482422,"game_num":48},{"timestamp":1581454578,"gametype_short":"ctf","rating":19.200000762939453,"game_num":49},{"timestamp":1581536846,"gametype_short":"ctf","rating":19.559999465942383,"game_num":50},{"timestamp":1581538730,"gametype_short":"ctf","rating":19.170000076293945,"game_num":51},{"timestamp":1581540343,"gametype_short":"ctf","rating":18.799999237060547,"game_num":52},{"timestamp":1581713537,"gametype_short":"ctf","rating":18.3700008392334,"game_num":53},{"timestamp":1581792956,"gametype_short":"ctf","rating":18.059999465942383,"game_num":54},{"timestamp":1581798130,"gametype_short":"ctf","rating":18.450000762939453,"game_num":55},{"timestamp":1581799888,"gametype_short":"ctf","rating":18.09000015258789,"game_num":56},{"timestamp":1581888550,"gametype_short":"ctf","rating":17.739999771118164,"game_num":57},{"timestamp":1581890867,"gametype_short":"ctf","rating":18.059999465942383,"game_num":58},{"timestamp":1581970058,"gametype_short":"ctf","rating":17.65999984741211,"game_num":59},{"timestamp":1581973756,"gametype_short":"ctf","rating":18,"game_num":60},{"timestamp":1581975414,"gametype_short":"ctf","rating":18.329999923706055,"game_num":61},{"timestamp":1581977219,"gametype_short":"ctf","rating":17.989999771118164,"game_num":62},{"timestamp":1582053420,"gametype_short":"ctf","rating":17.670000076293945,"game_num":63},{"timestamp":1582055321,"gametype_short":"ctf","rating":17.3799991607666,"game_num":64},{"timestamp":1582057283,"gametype_short":"ctf","rating":17.139999389648438,"game_num":65},{"timestamp":1582059046,"gametype_short":"ctf","rating":17.399999618530273,"game_num":66},{"timestamp":1582064332,"gametype_short":"ctf","rating":17.059999465942383,"game_num":67},{"timestamp":1582142744,"gametype_short":"ctf","rating":16.860000610351562,"game_num":68},{"timestamp":1582144338,"gametype_short":"ctf","rating":17.1200008392334,"game_num":69},{"timestamp":1582146020,"gametype_short":"ctf","rating":16.81999969482422,"game_num":70},{"timestamp":1582147873,"gametype_short":"ctf","rating":17.079999923706055,"game_num":71},{"timestamp":1582224734,"gametype_short":"ctf","rating":17.34000015258789,"game_num":72},{"timestamp":1582226515,"gametype_short":"ctf","rating":18.06999969482422,"game_num":73},{"timestamp":1582228866,"gametype_short":"ctf","rating":18.440000534057617,"game_num":74},{"timestamp":1582230933,"gametype_short":"ctf","rating":18.239999771118164,"game_num":75},{"timestamp":1582391099,"gametype_short":"ctf","rating":18.610000610351562,"game_num":76},{"timestamp":1582394170,"gametype_short":"ctf","rating":18.399999618530273,"game_num":77},{"timestamp":1582399559,"gametype_short":"ctf","rating":18.200000762939453,"game_num":78},{"timestamp":1582401506,"gametype_short":"ctf","rating":18.459999084472656,"game_num":79},{"timestamp":1582403369,"gametype_short":"ctf","rating":18.219999313354492,"game_num":80},{"timestamp":1582483176,"gametype_short":"ctf","rating":18,"game_num":81},{"timestamp":1582485634,"gametype_short":"ctf","rating":18.239999771118164,"game_num":82},{"timestamp":1582487990,"gametype_short":"ctf","rating":18.479999542236328,"game_num":83},{"timestamp":1582573554,"gametype_short":"ctf","rating":18.700000762939453,"game_num":84},{"timestamp":1582575272,"gametype_short":"ctf","rating":18.450000762939453,"game_num":85},{"timestamp":1582665554,"gametype_short":"ctf","rating":18.209999084472656,"game_num":86},{"timestamp":1582667287,"gametype_short":"ctf","rating":17.950000762939453,"game_num":87},{"timestamp":1582669019,"gametype_short":"ctf","rating":17.670000076293945,"game_num":88},{"timestamp":1582747033,"gametype_short":"ctf","rating":17.649999618530273,"game_num":89},{"timestamp":1582750711,"gametype_short":"ctf","rating":17.440000534057617,"game_num":90},{"timestamp":1582753139,"gametype_short":"ctf","rating":17.200000762939453,"game_num":91},{"timestamp":1582833434,"gametype_short":"ctf","rating":17.3700008392334,"game_num":92},{"timestamp":1582834862,"gametype_short":"ctf","rating":17.110000610351562,"game_num":93},{"timestamp":1582837009,"gametype_short":"ctf","rating":16.850000381469727,"game_num":94},{"timestamp":1582838727,"gametype_short":"ctf","rating":17.06999969482422,"game_num":95},{"timestamp":1582921547,"gametype_short":"ctf","rating":16.8799991607666,"game_num":96},{"timestamp":1582924461,"gametype_short":"ctf","rating":17.100000381469727,"game_num":97},{"timestamp":1582926482,"gametype_short":"ctf","rating":16.8799991607666,"game_num":98},{"timestamp":1583094431,"gametype_short":"ctf","rating":17.110000610351562,"game_num":99},{"timestamp":1583096218,"gametype_short":"ctf","rating":17.329999923706055,"game_num":100},{"timestamp":1583178886,"gametype_short":"ctf","rating":17.530000686645508,"game_num":101},{"timestamp":1583180605,"gametype_short":"ctf","rating":17.309999465942383,"game_num":102},{"timestamp":1583354805,"gametype_short":"ctf","rating":17.079999923706055,"game_num":103},{"timestamp":1583523930,"gametype_short":"ctf","rating":17.280000686645508,"game_num":104},{"timestamp":1583525804,"gametype_short":"ctf","rating":17.100000381469727,"game_num":105},{"timestamp":1583606828,"gametype_short":"ctf","rating":16.90999984741211,"game_num":106},{"timestamp":1583608642,"gametype_short":"ctf","rating":17.079999923706055,"game_num":107},{"timestamp":1583610321,"gametype_short":"ctf","rating":17.270000457763672,"game_num":108},{"timestamp":1583612183,"gametype_short":"ctf","rating":17.059999465942383,"game_num":109},{"timestamp":1583687095,"gametype_short":"ctf","rating":16.8700008392334,"game_num":110},{"timestamp":1583956233,"gametype_short":"ctf","rating":17.049999237060547,"game_num":111},{"timestamp":1583957938,"gametype_short":"ctf","rating":16.8799991607666,"game_num":112},{"timestamp":1584040114,"gametype_short":"ctf","rating":17.06999969482422,"game_num":113},{"timestamp":1584041945,"gametype_short":"ctf","rating":16.889999389648438,"game_num":114},{"timestamp":1584043886,"gametype_short":"ctf","rating":17.059999465942383,"game_num":115},{"timestamp":1584045646,"gametype_short":"ctf","rating":16.8700008392334,"game_num":116},{"timestamp":1584129568,"gametype_short":"ctf","rating":17.06999969482422,"game_num":117},{"timestamp":1584131344,"gametype_short":"ctf","rating":17.25,"game_num":118},{"timestamp":1584134534,"gametype_short":"ctf","rating":17.440000534057617,"game_num":119},{"timestamp":1584287237,"gametype_short":"ctf","rating":17.65999984741211,"game_num":120},{"timestamp":1584288972,"gametype_short":"ctf","rating":17.809999465942383,"game_num":121},{"timestamp":1584304851,"gametype_short":"ctf","rating":17.639999389648438,"game_num":122},{"timestamp":1584390738,"gametype_short":"ctf","rating":17.799999237060547,"game_num":123},{"timestamp":1584479384,"gametype_short":"ctf","rating":17.6200008392334,"game_num":124},{"timestamp":1584481098,"gametype_short":"ctf","rating":17.770000457763672,"game_num":125},{"timestamp":1584483002,"gametype_short":"ctf","rating":17.579999923706055,"game_num":126},{"timestamp":1584646141,"gametype_short":"ctf","rating":17.75,"game_num":127},{"timestamp":1584647742,"gametype_short":"ctf","rating":17.559999465942383,"game_num":128},{"timestamp":1584734940,"gametype_short":"ctf","rating":17.399999618530273,"game_num":129},{"timestamp":1584806180,"gametype_short":"ctf","rating":17.59000015258789,"game_num":130},{"timestamp":1584808469,"gametype_short":"ctf","rating":17.40999984741211,"game_num":131},{"timestamp":1584816090,"gametype_short":"ctf","rating":17.559999465942383,"game_num":132},{"timestamp":1584818065,"gametype_short":"ctf","rating":17.739999771118164,"game_num":133},{"timestamp":1584901387,"gametype_short":"ctf","rating":17.90999984741211,"game_num":134},{"timestamp":1584903160,"gametype_short":"ctf","rating":17.739999771118164,"game_num":135},{"timestamp":1584904969,"gametype_short":"ctf","rating":17.90999984741211,"game_num":136},{"timestamp":1584907090,"gametype_short":"ctf","rating":17.75,"game_num":137},{"timestamp":1584993267,"gametype_short":"ctf","rating":17.579999923706055,"game_num":138},{"timestamp":1584997423,"gametype_short":"ctf","rating":17.389999389648438,"game_num":139},{"timestamp":1584999059,"gametype_short":"ctf","rating":17.200000762939453,"game_num":140},{"timestamp":1585079124,"gametype_short":"ctf","rating":17.3799991607666,"game_num":141},{"timestamp":1585082407,"gametype_short":"ctf","rating":17.200000762939453,"game_num":142},{"timestamp":1585169380,"gametype_short":"ctf","rating":17.34000015258789,"game_num":143},{"timestamp":1585172481,"gametype_short":"ctf","rating":17.530000686645508,"game_num":144},{"timestamp":1585252625,"gametype_short":"ctf","rating":17.3700008392334,"game_num":145},{"timestamp":1585255753,"gametype_short":"ctf","rating":17.239999771118164,"game_num":146},{"timestamp":1585257591,"gametype_short":"ctf","rating":17.31999969482422,"game_num":147},{"timestamp":1585330453,"gametype_short":"ctf","rating":17.040000915527344,"game_num":148},{"timestamp":1585332317,"gametype_short":"ctf","rating":17.219999313354492,"game_num":149},{"timestamp":1585522877,"gametype_short":"ctf","rating":17.389999389648438,"game_num":150},{"timestamp":1585589701,"gametype_short":"ctf","rating":17.520000457763672,"game_num":151},{"timestamp":1585594813,"gametype_short":"ctf","rating":17.3799991607666,"game_num":152},{"timestamp":1585596350,"gametype_short":"ctf","rating":17.540000915527344,"game_num":153},{"timestamp":1585682000,"gametype_short":"ctf","rating":17.3700008392334,"game_num":154},{"timestamp":1585780816,"gametype_short":"ctf","rating":17.229999542236328,"game_num":155},{"timestamp":1585782682,"gametype_short":"ctf","rating":17.09000015258789,"game_num":156},{"timestamp":1585856823,"gametype_short":"ctf","rating":17.209999084472656,"game_num":157},{"timestamp":1585858982,"gametype_short":"ctf","rating":17.34000015258789,"game_num":158},{"timestamp":1585860778,"gametype_short":"ctf","rating":17.200000762939453,"game_num":159},{"timestamp":1585862591,"gametype_short":"ctf","rating":17.06999969482422,"game_num":160},{"timestamp":1585933702,"gametype_short":"ctf","rating":16.940000534057617,"game_num":161},{"timestamp":1585936810,"gametype_short":"ctf","rating":16.790000915527344,"game_num":162},{"timestamp":1586014006,"gametype_short":"ctf","rating":16.6299991607666,"game_num":163},{"timestamp":1586015912,"gametype_short":"ctf","rating":16.520000457763672,"game_num":164},{"timestamp":1586116858,"gametype_short":"ctf","rating":16.389999389648438,"game_num":165},{"timestamp":1586118754,"gametype_short":"ctf","rating":16.540000915527344,"game_num":166},{"timestamp":1586196927,"gametype_short":"ctf","rating":16.670000076293945,"game_num":167},{"timestamp":1586198603,"gametype_short":"ctf","rating":16.799999237060547,"game_num":168},{"timestamp":1586289411,"gametype_short":"ctf","rating":16.950000762939453,"game_num":169},{"timestamp":1586293037,"gametype_short":"ctf","rating":16.81999969482422,"game_num":170},{"timestamp":1586361673,"gametype_short":"ctf","rating":16.700000762939453,"game_num":171},{"timestamp":1586374098,"gametype_short":"ctf","rating":16.850000381469727,"game_num":172},{"timestamp":1586375884,"gametype_short":"ctf","rating":16.729999542236328,"game_num":173},{"timestamp":1586460608,"gametype_short":"ctf","rating":16.8700008392334,"game_num":174},{"timestamp":1586720289,"gametype_short":"ctf","rating":17.010000228881836,"game_num":175},{"timestamp":1586722763,"gametype_short":"ctf","rating":16.8799991607666,"game_num":176},{"timestamp":1586806689,"gametype_short":"ctf","rating":17.06999969482422,"game_num":177},{"timestamp":1586809055,"gametype_short":"ctf","rating":16.989999771118164,"game_num":178},{"timestamp":1586893870,"gametype_short":"ctf","rating":17.09000015258789,"game_num":179},{"timestamp":1586896228,"gametype_short":"ctf","rating":16.959999084472656,"game_num":180},{"timestamp":1586897865,"gametype_short":"ctf","rating":17.079999923706055,"game_num":181},{"timestamp":1586900042,"gametype_short":"ctf","rating":17.209999084472656,"game_num":182},{"timestamp":1586983752,"gametype_short":"ctf","rating":17.34000015258789,"game_num":183},{"timestamp":1586985666,"gametype_short":"ctf","rating":17.229999542236328,"game_num":184},{"timestamp":1587498120,"gametype_short":"ctf","rating":17.360000610351562,"game_num":185},{"timestamp":1587499906,"gametype_short":"ctf","rating":17.229999542236328,"game_num":186},{"timestamp":1587576752,"gametype_short":"ctf","rating":17.1299991607666,"game_num":187},{"timestamp":1587662713,"gametype_short":"ctf","rating":16.989999771118164,"game_num":188},{"timestamp":1587666519,"gametype_short":"ctf","rating":17.1200008392334,"game_num":189},{"timestamp":1587668402,"gametype_short":"ctf","rating":17.229999542236328,"game_num":190},{"timestamp":1587756445,"gametype_short":"ctf","rating":17.1200008392334,"game_num":191},{"timestamp":1587758954,"gametype_short":"ctf","rating":17.229999542236328,"game_num":192},{"timestamp":1587761091,"gametype_short":"ctf","rating":17.360000610351562,"game_num":193},{"timestamp":1587762779,"gametype_short":"ctf","rating":17.229999542236328,"game_num":194},{"timestamp":1587837912,"gametype_short":"ctf","rating":17.100000381469727,"game_num":195},{"timestamp":1587841789,"gametype_short":"ctf","rating":16.940000534057617,"game_num":196},{"timestamp":1587843937,"gametype_short":"ctf","rating":17.059999465942383,"game_num":197},{"timestamp":1587919058,"gametype_short":"ctf","rating":16.920000076293945,"game_num":198},{"timestamp":1587920983,"gametype_short":"ctf","rating":16.760000228881836,"game_num":199},{"timestamp":1587934825,"gametype_short":"ctf","rating":16.889999389648438,"game_num":200},{"timestamp":1587937313,"gametype_short":"ctf","rating":16.780000686645508,"game_num":201},{"timestamp":1588009824,"gametype_short":"ctf","rating":16.6299991607666,"game_num":202},{"timestamp":1588013396,"gametype_short":"ctf","rating":16.489999771118164,"game_num":203},{"timestamp":1588015089,"gametype_short":"ctf","rating":16.3700008392334,"game_num":204},{"timestamp":1588097446,"gametype_short":"ctf","rating":16.260000228881836,"game_num":205},{"timestamp":1588181466,"gametype_short":"ctf","rating":16.389999389648438,"game_num":206},{"timestamp":1588269972,"gametype_short":"ctf","rating":16.25,"game_num":207},{"timestamp":1588275641,"gametype_short":"ctf","rating":16.25,"game_num":208},{"timestamp":1588277503,"gametype_short":"ctf","rating":16.110000610351562,"game_num":209},{"timestamp":1588609786,"gametype_short":"ctf","rating":15.989999771118164,"game_num":210},{"timestamp":1588611631,"gametype_short":"ctf","rating":16.149999618530273,"game_num":211},{"timestamp":1588779381,"gametype_short":"ctf","rating":16.030000686645508,"game_num":212},{"timestamp":1589320166,"gametype_short":"ctf","rating":16.149999618530273,"game_num":213},{"timestamp":1589322281,"gametype_short":"ctf","rating":16.299999237060547,"game_num":214},{"timestamp":1589391779,"gametype_short":"ctf","rating":16.18000030517578,"game_num":215},{"timestamp":1589394551,"gametype_short":"ctf","rating":16.059999465942383,"game_num":216},{"timestamp":1589475989,"gametype_short":"ctf","rating":16.18000030517578,"game_num":217},{"timestamp":1589489757,"gametype_short":"ctf","rating":16.309999465942383,"game_num":218},{"timestamp":1589491442,"gametype_short":"ctf","rating":16.440000534057617,"game_num":219},{"timestamp":1589493352,"gametype_short":"ctf","rating":16.56999969482422,"game_num":220},{"timestamp":1589637915,"gametype_short":"ctf","rating":16.450000762939453,"game_num":221},{"timestamp":1589658229,"gametype_short":"ctf","rating":16.329999923706055,"game_num":222},{"timestamp":1589659931,"gametype_short":"ctf","rating":16.450000762939453,"game_num":223},{"timestamp":1590617651,"gametype_short":"ctf","rating":16.31999969482422,"game_num":224},{"timestamp":1590619688,"gametype_short":"ctf","rating":16.459999084472656,"game_num":225},{"timestamp":1591041991,"gametype_short":"ctf","rating":16.56999969482422,"game_num":226},{"timestamp":1591381235,"gametype_short":"ctf","rating":16.440000534057617,"game_num":227},{"timestamp":1591383691,"gametype_short":"ctf","rating":16.559999465942383,"game_num":228},{"timestamp":1591733131,"gametype_short":"ctf","rating":16.440000534057617,"game_num":229},{"timestamp":1591734756,"gametype_short":"ctf","rating":16.309999465942383,"game_num":230},{"timestamp":1591990823,"gametype_short":"ctf","rating":16.420000076293945,"game_num":231},{"timestamp":1591992668,"gametype_short":"ctf","rating":16.290000915527344,"game_num":232},{"timestamp":1592082017,"gametype_short":"ctf","rating":16.190000534057617,"game_num":233},{"timestamp":1592164514,"gametype_short":"ctf","rating":16.079999923706055,"game_num":234},{"timestamp":1592166267,"gametype_short":"ctf","rating":15.949999809265137,"game_num":235},{"timestamp":1592168203,"gametype_short":"ctf","rating":16.059999465942383,"game_num":236},{"timestamp":1592334313,"gametype_short":"ctf","rating":15.9399995803833,"game_num":237},{"timestamp":1592335983,"gametype_short":"ctf","rating":15.819999694824219,"game_num":238},{"timestamp":1592339283,"gametype_short":"ctf","rating":15.930000305175781,"game_num":239},{"timestamp":1592340978,"gametype_short":"ctf","rating":15.8100004196167,"game_num":240},{"timestamp":1592342863,"gametype_short":"ctf","rating":15.6899995803833,"game_num":241},{"timestamp":1592416826,"gametype_short":"ctf","rating":15.819999694824219,"game_num":242},{"timestamp":1592422268,"gametype_short":"ctf","rating":15.710000038146973,"game_num":243},{"timestamp":1592430114,"gametype_short":"ctf","rating":15.579999923706055,"game_num":244},{"timestamp":1592518168,"gametype_short":"ctf","rating":15.460000038146973,"game_num":245},{"timestamp":1592520024,"gametype_short":"ctf","rating":15.569999694824219,"game_num":246},{"timestamp":1592582595,"gametype_short":"ctf","rating":15.680000305175781,"game_num":247},{"timestamp":1592684234,"gametype_short":"ctf","rating":15.5600004196167,"game_num":248},{"timestamp":1592773236,"gametype_short":"ctf","rating":15.449999809265137,"game_num":249},{"timestamp":1592774848,"gametype_short":"ctf","rating":15.569999694824219,"game_num":250},{"timestamp":1592776583,"gametype_short":"ctf","rating":15.4399995803833,"game_num":251},{"timestamp":1592851927,"gametype_short":"ctf","rating":15.5600004196167,"game_num":252},{"timestamp":1592853722,"gametype_short":"ctf","rating":15.4399995803833,"game_num":253},{"timestamp":1592943241,"gametype_short":"ctf","rating":15.5600004196167,"game_num":254},{"timestamp":1592945065,"gametype_short":"ctf","rating":15.430000305175781,"game_num":255},{"timestamp":1593018198,"gametype_short":"tdm","rating":19.729999542236328,"game_num":4},{"timestamp":1593021782,"gametype_short":"tdm","rating":22.010000228881836,"game_num":5},{"timestamp":1593033559,"gametype_short":"ctf","rating":15.5600004196167,"game_num":256},{"timestamp":1593117195,"gametype_short":"ctf","rating":15.4399995803833,"game_num":257},{"timestamp":1593118901,"gametype_short":"ctf","rating":15.550000190734863,"game_num":258},{"timestamp":1593120764,"gametype_short":"ctf","rating":15.670000076293945,"game_num":259},{"timestamp":1593207744,"gametype_short":"ctf","rating":15.5600004196167,"game_num":260},{"timestamp":1593290153,"gametype_short":"ctf","rating":15.4399995803833,"game_num":261},{"timestamp":1593291904,"gametype_short":"ctf","rating":15.319999694824219,"game_num":262},{"timestamp":1593548292,"gametype_short":"ctf","rating":15.210000038146973,"game_num":263},{"timestamp":1593550146,"gametype_short":"ctf","rating":15.09000015258789,"game_num":264},{"timestamp":1593552052,"gametype_short":"ctf","rating":15.210000038146973,"game_num":265},{"timestamp":1593553839,"gametype_short":"ctf","rating":15.09000015258789,"game_num":266},{"timestamp":1593631068,"gametype_short":"ctf","rating":15.210000038146973,"game_num":267},{"timestamp":1593634625,"gametype_short":"ctf","rating":15.319999694824219,"game_num":268},{"timestamp":1593723134,"gametype_short":"ctf","rating":15.4399995803833,"game_num":269},{"timestamp":1593724860,"gametype_short":"ctf","rating":15.550000190734863,"game_num":270},{"timestamp":1593726669,"gametype_short":"ctf","rating":15.670000076293945,"game_num":271},{"timestamp":1593806114,"gametype_short":"ctf","rating":15.84000015258789,"game_num":272},{"timestamp":1593808097,"gametype_short":"ctf","rating":15.729999542236328,"game_num":273},{"timestamp":1593809945,"gametype_short":"ctf","rating":15.84000015258789,"game_num":274},{"timestamp":1593813086,"gametype_short":"ctf","rating":15.949999809265137,"game_num":275},{"timestamp":1593814934,"gametype_short":"ctf","rating":15.979999542236328,"game_num":276},{"timestamp":1593981560,"gametype_short":"ctf","rating":15.869999885559082,"game_num":277},{"timestamp":1593983139,"gametype_short":"ctf","rating":15.75,"game_num":278},{"timestamp":1594062939,"gametype_short":"ctf","rating":15.649999618530273,"game_num":279},{"timestamp":1594064679,"gametype_short":"ctf","rating":15.539999961853027,"game_num":280},{"timestamp":1594066568,"gametype_short":"ctf","rating":15.430000305175781,"game_num":281},{"timestamp":1594151192,"gametype_short":"ctf","rating":15.550000190734863,"game_num":282},{"timestamp":1594152989,"gametype_short":"ctf","rating":15.4399995803833,"game_num":283},{"timestamp":1595184753,"gametype_short":"ctf","rating":15.319999694824219,"game_num":284},{"timestamp":1595186694,"gametype_short":"ctf","rating":15.420000076293945,"game_num":285},{"timestamp":1597094239,"gametype_short":"ctf","rating":15.3100004196167,"game_num":286},{"timestamp":1598042702,"gametype_short":"ctf","rating":15.40999984741211,"game_num":287},{"timestamp":1598044748,"gametype_short":"ctf","rating":15.289999961853027,"game_num":288},{"timestamp":1598907714,"gametype_short":"ctf","rating":15.180000305175781,"game_num":289},{"timestamp":1598910199,"gametype_short":"ctf","rating":15.289999961853027,"game_num":290},{"timestamp":1598987538,"gametype_short":"ctf","rating":15.399999618530273,"game_num":291},{"timestamp":1598989404,"gametype_short":"ctf","rating":15.300000190734863,"game_num":292},{"timestamp":1598991934,"gametype_short":"ctf","rating":15.039999961853027,"game_num":293},{"timestamp":1599079939,"gametype_short":"ctf","rating":15.140000343322754,"game_num":294},{"timestamp":1599082303,"gametype_short":"ctf","rating":15.039999961853027,"game_num":295},{"timestamp":1602273859,"gametype_short":"ctf","rating":15.140000343322754,"game_num":296},{"timestamp":1602275427,"gametype_short":"ctf","rating":15.25,"game_num":297},{"timestamp":1602364801,"gametype_short":"ctf","rating":15.140000343322754,"game_num":298},{"timestamp":1602366982,"gametype_short":"ctf","rating":15.029999732971191,"game_num":299},{"timestamp":1602422362,"gametype_short":"ctf","rating":15.149999618530273,"game_num":300},{"timestamp":1602707656,"gametype_short":"ctf","rating":15.260000228881836,"game_num":301},{"timestamp":1607630467,"gametype_short":"tdm","rating":20.200000762939453,"game_num":6},{"timestamp":1607632927,"gametype_short":"tdm","rating":18.299999237060547,"game_num":7},{"timestamp":1607716950,"gametype_short":"tdm","rating":16.719999313354492,"game_num":8},{"timestamp":1607718920,"gametype_short":"ctf","rating":15.369999885559082,"game_num":302},{"timestamp":1607720756,"gametype_short":"ctf","rating":15.260000228881836,"game_num":303},{"timestamp":1607808061,"gametype_short":"ctf","rating":15.369999885559082,"game_num":304},{"timestamp":1607810473,"gametype_short":"ctf","rating":15.300000190734863,"game_num":305},{"timestamp":1607812393,"gametype_short":"ctf","rating":15.40999984741211,"game_num":306},{"timestamp":1607814453,"gametype_short":"ctf","rating":15.520000457763672,"game_num":307},{"timestamp":1607863577,"gametype_short":"tdm","rating":18.1299991607666,"game_num":9},{"timestamp":1607867233,"gametype_short":"tdm","rating":19.350000381469727,"game_num":10},{"timestamp":1607868446,"gametype_short":"tdm","rating":20.309999465942383,"game_num":11},{"timestamp":1607870110,"gametype_short":"tdm","rating":20.989999771118164,"game_num":12},{"timestamp":1607871423,"gametype_short":"tdm","rating":21.559999465942383,"game_num":13},{"timestamp":1607874415,"gametype_short":"tdm","rating":20.280000686645508,"game_num":14},{"timestamp":1607875579,"gametype_short":"tdm","rating":19.329999923706055,"game_num":15},{"timestamp":1607881145,"gametype_short":"tdm","rating":20.649999618530273,"game_num":16},{"timestamp":1607882492,"gametype_short":"tdm","rating":21.65999984741211,"game_num":17},{"timestamp":1607884731,"gametype_short":"tdm","rating":22.5,"game_num":18},{"timestamp":1607886122,"gametype_short":"tdm","rating":21.540000915527344,"game_num":19},{"timestamp":1607887871,"gametype_short":"tdm","rating":20.770000457763672,"game_num":20},{"timestamp":1609099516,"gametype_short":"ctf","rating":15.619999885559082,"game_num":308},{"timestamp":1609455421,"gametype_short":"ctf","rating":15.520000457763672,"game_num":309},{"timestamp":1609457942,"gametype_short":"ctf","rating":15.630000114440918,"game_num":310},{"timestamp":1610302627,"gametype_short":"ctf","rating":15.59000015258789,"game_num":311},{"timestamp":1612038145,"gametype_short":"tdm","rating":21.549999237060547,"game_num":21},{"timestamp":1612039707,"gametype_short":"tdm","rating":20.809999465942383,"game_num":22},{"timestamp":1612041259,"gametype_short":"tdm","rating":20.18000030517578,"game_num":23},{"timestamp":1612042919,"gametype_short":"tdm","rating":20.899999618530273,"game_num":24},{"timestamp":1612728796,"gametype_short":"tdm","rating":20.34000015258789,"game_num":25},{"timestamp":1616000215,"gametype_short":"tdm","rating":19.729999542236328,"game_num":26},{"timestamp":1616001807,"gametype_short":"tdm","rating":20.3700008392334,"game_num":27},{"timestamp":1616003523,"gametype_short":"tdm","rating":20.969999313354492,"game_num":28},{"timestamp":1616011150,"gametype_short":"tdm","rating":20.3700008392334,"game_num":29},{"timestamp":1616012913,"gametype_short":"tdm","rating":19.739999771118164,"game_num":30},{"timestamp":1616086659,"gametype_short":"tdm","rating":19.239999771118164,"game_num":31},{"timestamp":1616089394,"gametype_short":"tdm","rating":18.739999771118164,"game_num":32},{"timestamp":1616093025,"gametype_short":"tdm","rating":18.25,"game_num":33},{"timestamp":1616096465,"gametype_short":"tdm","rating":17.719999313354492,"game_num":34},{"timestamp":1616253990,"gametype_short":"tdm","rating":18.219999313354492,"game_num":35},{"timestamp":1616255888,"gametype_short":"tdm","rating":17.81999969482422,"game_num":36},{"timestamp":1616259696,"gametype_short":"tdm","rating":18.25,"game_num":37},{"timestamp":1616261822,"gametype_short":"tdm","rating":17.889999389648438,"game_num":38},{"timestamp":1616269403,"gametype_short":"tdm","rating":17.510000228881836,"game_num":39},{"timestamp":1616271723,"gametype_short":"tdm","rating":17.8799991607666,"game_num":40},{"timestamp":1616354266,"gametype_short":"tdm","rating":17.510000228881836,"game_num":41},{"timestamp":1616357184,"gametype_short":"tdm","rating":17.90999984741211,"game_num":42},{"timestamp":1616359118,"gametype_short":"tdm","rating":18.290000915527344,"game_num":43},{"timestamp":1616781021,"gametype_short":"tdm","rating":17.93000030517578,"game_num":44},{"timestamp":1616785267,"gametype_short":"tdm","rating":17.540000915527344,"game_num":45},{"timestamp":1624794152,"gametype_short":"ctf","rating":15.479999542236328,"game_num":312},{"timestamp":1624796028,"gametype_short":"ctf","rating":15.390000343322754,"game_num":313},{"timestamp":1624797762,"gametype_short":"ctf","rating":15.279999732971191,"game_num":314},{"timestamp":1624804818,"gametype_short":"ctf","rating":15.390000343322754,"game_num":315},{"timestamp":1624809019,"gametype_short":"ctf","rating":15.479999542236328,"game_num":316},{"timestamp":1624810601,"gametype_short":"ctf","rating":15.380000114440918,"game_num":317},{"timestamp":1626294299,"gametype_short":"ctf","rating":15.489999771118164,"game_num":318},{"timestamp":1626295852,"gametype_short":"ctf","rating":15.600000381469727,"game_num":319},{"timestamp":1626297609,"gametype_short":"ctf","rating":15.5,"game_num":320},{"timestamp":1626379877,"gametype_short":"tdm","rating":17.260000228881836,"game_num":46},{"timestamp":1626468092,"gametype_short":"ctf","rating":15.399999618530273,"game_num":321},{"timestamp":1626470200,"gametype_short":"ctf","rating":15.5,"game_num":322},{"timestamp":1626551852,"gametype_short":"ctf","rating":15.600000381469727,"game_num":323},{"timestamp":1626553725,"gametype_short":"ctf","rating":15.710000038146973,"game_num":324},{"timestamp":1626626180,"gametype_short":"ctf","rating":15.609999656677246,"game_num":325},{"timestamp":1626637853,"gametype_short":"ctf","rating":15.510000228881836,"game_num":326},{"timestamp":1626639786,"gametype_short":"ctf","rating":15.609999656677246,"game_num":327},{"timestamp":1629829238,"gametype_short":"ctf","rating":15.720000267028809,"game_num":328},{"timestamp":1629831862,"gametype_short":"tdm","rating":17.639999389648438,"game_num":47},{"timestamp":1658867876,"gametype_short":"tdm","rating":17.969999313354492,"game_num":48},{"timestamp":1658869631,"gametype_short":"tdm","rating":17.610000610351562,"game_num":49},{"timestamp":1658873302,"gametype_short":"tdm","rating":17.979999542236328,"game_num":50},{"timestamp":1658875119,"gametype_short":"tdm","rating":17.6299991607666,"game_num":51},{"timestamp":1658959595,"gametype_short":"tdm","rating":17.290000915527344,"game_num":52},{"timestamp":1658961489,"gametype_short":"tdm","rating":17.559999465942383,"game_num":53},{"timestamp":1659046211,"gametype_short":"ctf","rating":15.819999694824219,"game_num":329},{"timestamp":1662150480,"gametype_short":"tdm","rating":17.889999389648438,"game_num":54},{"timestamp":1662151824,"gametype_short":"tdm","rating":17.59000015258789,"game_num":55},{"timestamp":1662672704,"gametype_short":"tdm","rating":17.299999237060547,"game_num":56},{"timestamp":1662927854,"gametype_short":"tdm","rating":17.100000381469727,"game_num":57},{"timestamp":1662930013,"gametype_short":"tdm","rating":16.770000457763672,"game_num":58},{"timestamp":1663020126,"gametype_short":"tdm","rating":16.459999084472656,"game_num":59},{"timestamp":1663090276,"gametype_short":"tdm","rating":16.190000534057617,"game_num":60},{"timestamp":1663091976,"gametype_short":"tdm","rating":15.899999618530273,"game_num":61},{"timestamp":1663190053,"gametype_short":"tdm","rating":15.609999656677246,"game_num":62},{"timestamp":1663191878,"gametype_short":"tdm","rating":15.899999618530273,"game_num":63},{"timestamp":1663276441,"gametype_short":"tdm","rating":15.670000076293945,"game_num":64},{"timestamp":1663279589,"gametype_short":"ctf","rating":15.930000305175781,"game_num":330},{"timestamp":1663443867,"gametype_short":"tdm","rating":15.9399995803833,"game_num":65},{"timestamp":1663446381,"gametype_short":"tdm","rating":15.670000076293945,"game_num":66},{"timestamp":1663448000,"gametype_short":"tdm","rating":15.380000114440918,"game_num":67},{"timestamp":1663540566,"gametype_short":"tdm","rating":15.65999984741211,"game_num":68},{"timestamp":1663613836,"gametype_short":"tdm","rating":15.399999618530273,"game_num":69},{"timestamp":1663615889,"gametype_short":"tdm","rating":15.15999984741211,"game_num":70},{"timestamp":1663706433,"gametype_short":"tdm","rating":14.890000343322754,"game_num":71},{"timestamp":1663707800,"gametype_short":"tdm","rating":14.630000114440918,"game_num":72},{"timestamp":1663709504,"gametype_short":"tdm","rating":14.390000343322754,"game_num":73},{"timestamp":1663794460,"gametype_short":"tdm","rating":14.15999984741211,"game_num":74},{"timestamp":1663796253,"gametype_short":"tdm","rating":14.170000076293945,"game_num":75},{"timestamp":1663975019,"gametype_short":"tdm","rating":14.40999984741211,"game_num":76},{"timestamp":1664058482,"gametype_short":"tdm","rating":14.619999885559082,"game_num":77},{"timestamp":1664060511,"gametype_short":"tdm","rating":14.829999923706055,"game_num":78},{"timestamp":1664311033,"gametype_short":"tdm","rating":15.109999656677246,"game_num":79},{"timestamp":1664312807,"gametype_short":"tdm","rating":14.880000114440918,"game_num":80},{"timestamp":1664399243,"gametype_short":"ctf","rating":15.829999923706055,"game_num":331},{"timestamp":1664401847,"gametype_short":"ctf","rating":15.9399995803833,"game_num":332},{"timestamp":1664729350,"gametype_short":"tdm","rating":14.600000381469727,"game_num":81},{"timestamp":1664730873,"gametype_short":"tdm","rating":14.869999885559082,"game_num":82},{"timestamp":1664732765,"gametype_short":"tdm","rating":14.649999618530273,"game_num":83},{"timestamp":1664734471,"gametype_short":"tdm","rating":14.430000305175781,"game_num":84},{"timestamp":1664903953,"gametype_short":"ctf","rating":16.040000915527344,"game_num":333},{"timestamp":1664905676,"gametype_short":"ctf","rating":16.149999618530273,"game_num":334},{"timestamp":1665840968,"gametype_short":"tdm","rating":14.619999885559082,"game_num":85},{"timestamp":1666125854,"gametype_short":"tdm","rating":14.890000343322754,"game_num":86},{"timestamp":1668287630,"gametype_short":"ctf","rating":16.139999389648438,"game_num":335},{"timestamp":1673545074,"gametype_short":"tdm","rating":14.680000305175781,"game_num":87},{"timestamp":1673548533,"gametype_short":"tdm","rating":14.890000343322754,"game_num":88},{"timestamp":1673550041,"gametype_short":"tdm","rating":15.100000381469727,"game_num":89},{"timestamp":1673558285,"gametype_short":"tdm","rating":14.90999984741211,"game_num":90},{"timestamp":1673643641,"gametype_short":"tdm","rating":14.699999809265137,"game_num":91},{"timestamp":1673645278,"gametype_short":"tdm","rating":14.84000015258789,"game_num":92},{"timestamp":1673724935,"gametype_short":"tdm","rating":14.640000343322754,"game_num":93},{"timestamp":1673736011,"gametype_short":"tdm","rating":14.770000457763672,"game_num":94},{"timestamp":1673737558,"gametype_short":"tdm","rating":14.569999694824219,"game_num":95},{"timestamp":1674164629,"gametype_short":"ctf","rating":16.25,"game_num":336},{"timestamp":1674166575,"gametype_short":"ctf","rating":16.149999618530273,"game_num":337},{"timestamp":1680808678,"gametype_short":"ctf","rating":16.049999237060547,"game_num":338},{"timestamp":1681897775,"gametype_short":"ca","rating":26.81999969482422,"game_num":1},{"timestamp":1681898813,"gametype_short":"ca","rating":31.780000686645508,"game_num":2},{"timestamp":1682094001,"gametype_short":"ca","rating":28.790000915527344,"game_num":3},{"timestamp":1682094766,"gametype_short":"ca","rating":30.309999465942383,"game_num":4},{"timestamp":1682095680,"gametype_short":"ca","rating":27.389999389648438,"game_num":5},{"timestamp":1702157706,"gametype_short":"tdm","rating":14.380000114440918,"game_num":96},{"timestamp":1711230524,"gametype_short":"tdm","rating":14.199999809265137,"game_num":97},{"timestamp":1730754127,"gametype_short":"tdm","rating":13.9399995803833,"game_num":98},{"timestamp":1730756063,"gametype_short":"ctf","rating":15.8100004196167,"game_num":339},{"timestamp":1730829676,"gametype_short":"ctf","rating":15.569999694824219,"game_num":340},{"timestamp":1730833845,"gametype_short":"ctf","rating":15.34000015258789,"game_num":341},{"timestamp":1731442937,"gametype_short":"tdm","rating":13.699999809265137,"game_num":99},{"timestamp":1731445672,"gametype_short":"tdm","rating":13.460000038146973,"game_num":100},{"timestamp":1731793166,"gametype_short":"tdm","rating":13.6899995803833,"game_num":101},{"timestamp":1731963193,"gametype_short":"ctf","rating":15.079999923706055,"game_num":342},{"timestamp":1732049896,"gametype_short":"tdm","rating":13.430000305175781,"game_num":102},{"timestamp":1732221255,"gametype_short":"ctf","rating":14.869999885559082,"game_num":343},{"timestamp":1732223173,"gametype_short":"tdm","rating":13.180000305175781,"game_num":103},{"timestamp":1732390942,"gametype_short":"ctf","rating":14.649999618530273,"game_num":344},{"timestamp":1732392504,"gametype_short":"ctf","rating":14.430000305175781,"game_num":345},{"timestamp":1732477617,"gametype_short":"tdm","rating":12.9399995803833,"game_num":104},{"timestamp":1732479538,"gametype_short":"tdm","rating":13.180000305175781,"game_num":105},{"timestamp":1732571432,"gametype_short":"ctf","rating":14.210000038146973,"game_num":346},{"timestamp":1732573091,"gametype_short":"ctf","rating":14,"game_num":347},{"timestamp":1732830130,"gametype_short":"ctf","rating":13.779999732971191,"game_num":348},{"timestamp":1733001830,"gametype_short":"tdm","rating":13.4399995803833,"game_num":106},{"timestamp":1733003339,"gametype_short":"tdm","rating":13.229999542236328,"game_num":107},{"timestamp":1733260696,"gametype_short":"ctf","rating":13.569999694824219,"game_num":349},{"timestamp":1733350427,"gametype_short":"ctf","rating":13.800000190734863,"game_num":350},{"timestamp":1733424783,"gametype_short":"ctf","rating":14,"game_num":351},{"timestamp":1733426457,"gametype_short":"ctf","rating":14.210000038146973,"game_num":352},{"timestamp":1733431372,"gametype_short":"ctf","rating":14,"game_num":353},{"timestamp":1733586382,"gametype_short":"tdm","rating":13.479999542236328,"game_num":108},{"timestamp":1733588571,"gametype_short":"tdm","rating":13.260000228881836,"game_num":109},{"timestamp":1733592401,"gametype_short":"tdm","rating":13.029999732971191,"game_num":110},{"timestamp":1733594724,"gametype_short":"tdm","rating":13.25,"game_num":111},{"timestamp":1733600604,"gametype_short":"tdm","rating":13.460000038146973,"game_num":112},{"timestamp":1733681125,"gametype_short":"ctf","rating":13.800000190734863,"game_num":354},{"timestamp":1733687699,"gametype_short":"ctf","rating":13.600000381469727,"game_num":355},{"timestamp":1733689769,"gametype_short":"ctf","rating":13.800000190734863,"game_num":356},{"timestamp":1733777693,"gametype_short":"ctf","rating":14,"game_num":357},{"timestamp":1733858300,"gametype_short":"ctf","rating":13.800000190734863,"game_num":358},{"timestamp":1733863534,"gametype_short":"ctf","rating":13.989999771118164,"game_num":359},{"timestamp":1733865847,"gametype_short":"ctf","rating":14.1899995803833,"game_num":360},{"timestamp":1733950727,"gametype_short":"ctf","rating":14,"game_num":361},{"timestamp":1733952274,"gametype_short":"ctf","rating":13.819999694824219,"game_num":362},{"timestamp":1734028716,"gametype_short":"ctf","rating":13.619999885559082,"game_num":363},{"timestamp":1734037040,"gametype_short":"ctf","rating":13.4399995803833,"game_num":364},{"timestamp":1734468051,"gametype_short":"ctf","rating":13.25,"game_num":365},{"timestamp":1734555468,"gametype_short":"ctf","rating":13.430000305175781,"game_num":366},{"timestamp":1734557346,"gametype_short":"ctf","rating":13.239999771118164,"game_num":367},{"timestamp":1734638918,"gametype_short":"ctf","rating":13.430000305175781,"game_num":368},{"timestamp":1734640746,"gametype_short":"ctf","rating":13.239999771118164,"game_num":369},{"timestamp":1734900541,"gametype_short":"ctf","rating":13.0600004196167,"game_num":370},{"timestamp":1734902214,"gametype_short":"ctf","rating":12.880000114440918,"game_num":371},{"timestamp":1735772702,"gametype_short":"ctf","rating":12.670000076293945,"game_num":372},{"timestamp":1736018293,"gametype_short":"ctf","rating":12.890000343322754,"game_num":373},{"timestamp":1736627892,"gametype_short":"ctf","rating":12.670000076293945,"game_num":374},{"timestamp":1736629017,"gametype_short":"ctf","rating":12.899999618530273,"game_num":375},{"timestamp":1737240994,"gametype_short":"ctf","rating":12.6899995803833,"game_num":376},{"timestamp":1737316071,"gametype_short":"ctf","rating":12.5,"game_num":377},{"timestamp":1737317629,"gametype_short":"ctf","rating":12.279999732971191,"game_num":378},{"timestamp":1737488873,"gametype_short":"ctf","rating":12.5,"game_num":379},{"timestamp":1737492111,"gametype_short":"ctf","rating":12.720000267028809,"game_num":380},{"timestamp":1737493800,"gametype_short":"ctf","rating":12.5,"game_num":381},{"timestamp":1737578312,"gametype_short":"tdm","rating":13.710000038146973,"game_num":113},{"timestamp":1737581147,"gametype_short":"ctf","rating":12.6899995803833,"game_num":382},{"timestamp":1737664007,"gametype_short":"ctf","rating":12.90999984741211,"game_num":383},{"timestamp":1737923728,"gametype_short":"ctf","rating":13.119999885559082,"game_num":384},{"timestamp":1737927119,"gametype_short":"ctf","rating":12.90999984741211,"game_num":385},{"timestamp":1738013834,"gametype_short":"ctf","rating":12.699999809265137,"game_num":386},{"timestamp":1775939949,"gametype_short":"tdm","rating":13.970000267028809,"game_num":114},{"timestamp":1775943429,"gametype_short":"tdm","rating":14.25,"game_num":115},{"timestamp":1775944703,"gametype_short":"tdm","rating":14,"game_num":116},{"timestamp":1775945951,"gametype_short":"tdm","rating":13.75,"game_num":117},{"timestamp":1776116761,"gametype_short":"tdm","rating":13.489999771118164,"game_num":118},{"timestamp":1776118380,"gametype_short":"tdm","rating":13.729999542236328,"game_num":119},{"timestamp":1776375558,"gametype_short":"tdm","rating":13.869999885559082,"game_num":120},{"timestamp":1776377759,"gametype_short":"tdm","rating":13.630000114440918,"game_num":121},{"timestamp":1776462121,"gametype_short":"tdm","rating":13.880000114440918,"game_num":122},{"timestamp":1776517172,"gametype_short":"tdm","rating":13.670000076293945,"game_num":123},{"timestamp":1776519430,"gametype_short":"tdm","rating":13.899999618530273,"game_num":124},{"timestamp":1776526260,"gametype_short":"tdm","rating":14.130000114440918,"game_num":125},{"timestamp":1776529861,"gametype_short":"tdm","rating":14.350000381469727,"game_num":126},{"timestamp":1776633959,"gametype_short":"tdm","rating":14.569999694824219,"game_num":127},{"timestamp":1776635986,"gametype_short":"tdm","rating":14.350000381469727,"game_num":128},{"timestamp":1776708960,"gametype_short":"tdm","rating":14.5600004196167,"game_num":129},{"timestamp":1776710614,"gametype_short":"tdm","rating":14.350000381469727,"game_num":130},{"timestamp":1776720570,"gametype_short":"tdm","rating":14.520000457763672,"game_num":131},{"timestamp":1776978394,"gametype_short":"tdm","rating":14.729999542236328,"game_num":132},{"timestamp":1776980399,"gametype_short":"tdm","rating":14.529999732971191,"game_num":133},{"timestamp":1777150786,"gametype_short":"tdm","rating":14.6899995803833,"game_num":134},{"timestamp":1777152476,"gametype_short":"tdm","rating":14.470000267028809,"game_num":135},{"timestamp":1777154332,"gametype_short":"tdm","rating":14.270000457763672,"game_num":136},{"timestamp":1777217263,"gametype_short":"tdm","rating":14.079999923706055,"game_num":137},{"timestamp":1777218949,"gametype_short":"tdm","rating":13.890000343322754,"game_num":138},{"timestamp":1777220512,"gametype_short":"tdm","rating":13.699999809265137,"game_num":139},{"timestamp":1777327360,"gametype_short":"tdm","rating":13.520000457763672,"game_num":140},{"timestamp":1777329870,"gametype_short":"tdm","rating":13.390000343322754,"game_num":141},{"timestamp":1777399831,"gametype_short":"tdm","rating":13.210000038146973,"game_num":142},{"timestamp":1777401624,"gametype_short":"tdm","rating":13.029999732971191,"game_num":143},{"timestamp":1777573869,"gametype_short":"tdm","rating":12.850000381469727,"game_num":144},{"timestamp":1777575800,"gametype_short":"tdm","rating":13.050000190734863,"game_num":145},{"timestamp":1777671187,"gametype_short":"tdm","rating":12.859999656677246,"game_num":146},{"timestamp":1777673285,"gametype_short":"tdm","rating":13.050000190734863,"game_num":147},{"timestamp":1777747947,"gametype_short":"tdm","rating":12.859999656677246,"game_num":148},{"timestamp":1777749744,"gametype_short":"tdm","rating":13.039999961853027,"game_num":149},{"timestamp":1777755419,"gametype_short":"tdm","rating":12.859999656677246,"game_num":150},{"timestamp":1777756900,"gametype_short":"tdm","rating":13.010000228881836,"game_num":151},{"timestamp":1777760145,"gametype_short":"tdm","rating":12.819999694824219,"game_num":152},{"timestamp":1777927421,"gametype_short":"tdm","rating":12.649999618530273,"game_num":153},{"timestamp":1777929731,"gametype_short":"tdm","rating":12.479999542236328,"game_num":154},{"timestamp":1777931465,"gametype_short":"tdm","rating":12.630000114440918,"game_num":155},{"timestamp":1778101917,"gametype_short":"tdm","rating":12.800000190734863,"game_num":156},{"timestamp":1778103572,"gametype_short":"tdm","rating":12.630000114440918,"game_num":157},{"timestamp":1778105252,"gametype_short":"tdm","rating":12.470000267028809,"game_num":158},{"timestamp":1778187248,"gametype_short":"tdm","rating":12.619999885559082,"game_num":159},{"timestamp":1778189208,"gametype_short":"tdm","rating":12.420000076293945,"game_num":160},{"timestamp":1778276996,"gametype_short":"tdm","rating":12.25,"game_num":161},{"timestamp":1778365577,"gametype_short":"tdm","rating":12.109999656677246,"game_num":162},{"timestamp":1778448061,"gametype_short":"tdm","rating":12.260000228881836,"game_num":163},{"timestamp":1778449833,"gametype_short":"tdm","rating":12.09000015258789,"game_num":164},{"timestamp":1778451601,"gametype_short":"tdm","rating":11.930000305175781,"game_num":165},{"timestamp":1778537357,"gametype_short":"tdm","rating":11.760000228881836,"game_num":166},{"timestamp":1778621855,"gametype_short":"tdm","rating":11.90999984741211,"game_num":167},{"timestamp":1778623785,"gametype_short":"tdm","rating":11.729999542236328,"game_num":168},{"timestamp":1778625480,"gametype_short":"tdm","rating":11.890000343322754,"game_num":169},{"timestamp":1778794935,"gametype_short":"tdm","rating":11.739999771118164,"game_num":170},{"timestamp":1778797551,"gametype_short":"tdm","rating":11.59000015258789,"game_num":171},{"timestamp":1778880842,"gametype_short":"tdm","rating":11.75,"game_num":172},{"timestamp":1778882886,"gametype_short":"tdm","rating":11.59000015258789,"game_num":173},{"timestamp":1778961159,"gametype_short":"tdm","rating":11.739999771118164,"game_num":174},{"timestamp":1778963850,"gametype_short":"tdm","rating":11.90999984741211,"game_num":175},{"timestamp":1779486009,"gametype_short":"tdm","rating":11.789999961853027,"game_num":176},{"timestamp":1779563796,"gametype_short":"tdm","rating":11.609999656677246,"game_num":177},{"timestamp":1779574954,"gametype_short":"tdm","rating":11.779999732971191,"game_num":178},{"timestamp":1779655435,"gametype_short":"ctf","rating":12.470000267028809,"game_num":387},{"timestamp":1779657375,"gametype_short":"tdm","rating":11.9399995803833,"game_num":179},{"timestamp":1779997882,"gametype_short":"tdm","rating":12.119999885559082,"game_num":180},{"timestamp":1780437343,"gametype_short":"tdm","rating":11.979999542236328,"game_num":181},{"timestamp":1780438989,"gametype_short":"tdm","rating":11.850000381469727,"game_num":182}]